README.md
setup.py
src/sentry_bot/__init__.py
src/sentry_bot/forms.py
src/sentry_bot/plugin.py
src/sentry_wechat_bot.egg-info/PKG-INFO
src/sentry_wechat_bot.egg-info/SOURCES.txt
src/sentry_wechat_bot.egg-info/dependency_links.txt
src/sentry_wechat_bot.egg-info/entry_points.txt
src/sentry_wechat_bot.egg-info/not-zip-safe
src/sentry_wechat_bot.egg-info/requires.txt
src/sentry_wechat_bot.egg-info/top_level.txt