Metadata-Version: 2.1
Name: sentry-wechat-bot
Version: 0.0.1
Summary: A Sentry extension which send errors stats to DingDing or Wechat
Home-page: https://github.com/Hsia1993/sentry-dingding
Author: phil.xia
Author-email: hsia1993@gmail.com
License: MIT
Keywords: sentry dingding
Platform: UNKNOWN
Classifier: Programming Language :: Python :: 2.7
Classifier: License :: OSI Approved :: MIT License
